oxapay/__init__.py
oxapay/client.py
oxapay/exceptions.py
oxapay/py.typed
oxapay/sync.py
oxapay/webhook.py
oxapay/models/__init__.py
oxapay/models/balance.py
oxapay/models/base.py
oxapay/models/exchange.py
oxapay/models/merchant.py
oxapay/models/payout.py
oxapay/models/system.py
oxapay-0.2.1.dist-info/METADATA
oxapay-0.2.1.dist-info/WHEEL
oxapay-0.2.1.dist-info/licenses/LICENSE
oxapay-0.2.1.dist-info/RECORD
