Metadata-Version: 2.4
Name: oxapay
Version: 0.2.1
Summary: A fully-typed asynchronous Python client for interacting with the OxaPay cryptocurrency payment gateway.
Project-URL: Homepage, https://codeberg.org/TheKaram/PyOxapay
Project-URL: Bug Tracker, https://codeberg.org/TheKaram/PyOxapay/issues
Project-URL: Documentation, https://codeberg.org/TheKaram/PyOxapay
Project-URL: Source Code, https://codeberg.org/TheKaram/PyOxapay
Author-email: Karam <karam.47w6v@aleeas.com>
License: MIT License
License-File: LICENSE
Keywords: bitcoin,blockchain,crypto,cryptocurrency,oxapay,payment
Classifier: Development Status :: 4 - Beta
Classifier: Intended Audience :: Developers
Classifier: License :: OSI Approved :: MIT License
Classifier: Programming Language :: Python :: 3
Classifier: Programming Language :: Python :: 3.13
Classifier: Topic :: Office/Business :: Financial
Classifier: Topic :: Software Development :: Libraries :: Python Modules
Requires-Python: >=3.10
Requires-Dist: aiohttp>=3.11.13
Requires-Dist: pydantic>=2.10.6
Provides-Extra: dev
Requires-Dist: ipython>=8.34.0; extra == 'dev'
Provides-Extra: webhook
Requires-Dist: fastapi>=0.115.11; extra == 'webhook'
Requires-Dist: uvicorn[standard]>=0.34.0; extra == 'webhook'
